{"AccountPagesEnabled":false,"AccountPagesPathPrefix":null,"AccountPagesAccessDeniedPath":null,"AccountPagesRedirectOnLogin":false,"ContentGroups":[{"AccessDeniedPath":"no-access","ContentGroupItems":[{"Pattern":"vault","MatchMode":2},{"Pattern":"video","MatchMode":2},{"Pattern":"tools","MatchMode":2},{"Pattern":"basics","MatchMode":2},{"Pattern":"resource","MatchMode":2},{"Pattern":"type","MatchMode":2},{"Pattern":"icons","MatchMode":2}],"AllowedPlans":[{"PostLoginPath":null,"Uid":"gWKZg09p"},{"PostLoginPath":null,"Uid":"z9M1L794"},{"PostLoginPath":null,"Uid":"rQVLyeW6"},{"PostLoginPath":null,"Uid":"dQG8oE94"}],"AllowedAddOns":[]},{"AccessDeniedPath":"no-access","ContentGroupItems":[{"Pattern":"preview","MatchMode":2}],"AllowedPlans":[{"PostLoginPath":null,"Uid":"dQG8oE94"}],"AllowedAddOns":[]}],"MagicLinkApiKey":null,"OidcClients":[],"Plans":[]}